setup.py
dsnd_probbbb/Binomialdistribution.py
dsnd_probbbb/Gaussiandistribution.py
dsnd_probbbb/Generaldistribution.py
dsnd_probbbb/__init__.py
dsnd_probbbb.egg-info/PKG-INFO
dsnd_probbbb.egg-info/SOURCES.txt
dsnd_probbbb.egg-info/dependency_links.txt
dsnd_probbbb.egg-info/not-zip-safe
dsnd_probbbb.egg-info/top_level.txt