Metadata-Version: 1.0
Name: dsnd-probbbb
Version: 0.2
Summary: Gaussian distributions
Home-page: UNKNOWN
Author: Bamigbade Opeyemi
Author-email: bamigbadeopeyemi@gmail.com
License: UNKNOWN
Platform: UNKNOWN
